dharitri_sdk_core/__init__.py
dharitri_sdk_core/account.py
dharitri_sdk_core/account_test.py
dharitri_sdk_core/address.py
dharitri_sdk_core/address_test.py
dharitri_sdk_core/bech32.py
dharitri_sdk_core/code_metadata.py
dharitri_sdk_core/code_metadata_test.py
dharitri_sdk_core/codec.py
dharitri_sdk_core/constants.py
dharitri_sdk_core/contract_query.py
dharitri_sdk_core/contract_query_builder.py
dharitri_sdk_core/contract_query_builder_test.py
dharitri_sdk_core/errors.py
dharitri_sdk_core/interfaces.py
dharitri_sdk_core/message.py
dharitri_sdk_core/message_test.py
dharitri_sdk_core/serializer.py
dharitri_sdk_core/token_payment.py
dharitri_sdk_core/token_payment_test.py
dharitri_sdk_core/tokens.py
dharitri_sdk_core/tokens_test.py
dharitri_sdk_core/transaction.py
dharitri_sdk_core/transaction_payload.py
dharitri_sdk_core/transaction_test.py
dharitri_sdk_core/typecheck.py
dharitri_sdk_core/proto/__init__.py
dharitri_sdk_core/proto/transaction.proto
dharitri_sdk_core/proto/transaction_pb2.py
dharitri_sdk_core/proto/transaction_pb2.pyi
dharitri_sdk_core/proto/transaction_serializer.py
dharitri_sdk_core/proto/transaction_serializer_test.py
dharitri_sdk_core/testutils/wallets.py
dharitri_sdk_core/testutils/testdata/adder.wasm
dharitri_sdk_core/testutils/testwallets/alice.pem
dharitri_sdk_core/testutils/testwallets/bob.pem
dharitri_sdk_core/testutils/testwallets/carol.pem
dharitri_sdk_core/testutils/testwallets/frank.pem
dharitri_sdk_core/testutils/testwallets/grace.pem
dharitri_sdk_core/transaction_builders/__init__.py
dharitri_sdk_core/transaction_builders/contract_builders.py
dharitri_sdk_core/transaction_builders/contract_builders_test.py
dharitri_sdk_core/transaction_builders/dct_builders.py
dharitri_sdk_core/transaction_builders/dct_builders_test.py
dharitri_sdk_core/transaction_builders/default_configuration.py
dharitri_sdk_core/transaction_builders/default_configuration_test.py
dharitri_sdk_core/transaction_builders/other_builders.py
dharitri_sdk_core-0.0.6.dist-info/METADATA
dharitri_sdk_core-0.0.6.dist-info/WHEEL
dharitri_sdk_core-0.0.6.dist-info/licenses/LICENSE
dharitri_sdk_core-0.0.6.dist-info/RECORD
