Metadata-Version: 2.3
Name: dharitri-sdk-core
Version: 0.0.6
Summary: Core components of the Dharitri Python SDK.
Project-URL: Homepage, https://github.com/Dharitri-org/drt-sdk-py-core
Author: Dharitri
License-Expression: MIT
License-File: LICENSE
Classifier: License :: OSI Approved :: MIT License
Classifier: Operating System :: OS Independent
Classifier: Programming Language :: Python :: 3
Requires-Python: >=3.8
Requires-Dist: protobuf==3.20.1
Requires-Dist: pycryptodomex==3.16.0
